ktsessions
