Metadata-Version: 1.0
Name: kt-flask-sessions
Version: 0.1.1
Summary: Kyoto Tycoon backed sessions for Flask
Home-page: https://github.com/qpfiffer/KyotoTycoonFlaskSessions
Author: Quinlan Pfiffer
Author-email: qpfiffer@gmail.com
License: BSD
Keywords: Kyoto Tycoon,Flask
Platform: UNKNOWN
